{
  "applicability_gold": {
    "gold_file": "applicability_gold_eval_v1.json"
  },
  "compliance_gold": {
    "gold_file": "compliance_gold_eval_v1.json"
  },
  "coverage_thresholds": {
    "applicability_gold_case_count_min": 12,
    "compliance_gold_case_count_min": 14,
    "distinct_forest_count_min": 2,
    "distinct_package_style_count_min": 3,
    "missing_package_authority_count_max": 0,
    "missing_required_review_contract_count_max": 0,
    "required_high_priority_family_id_count": 19,
    "required_review_contract_count": 3,
    "required_theme_count": 7,
    "reviewer_ready_review_count_min": 2,
    "typed_blocked_review_count_min": 1,
    "unmapped_high_priority_family_count_max": 0
  },
  "id": "region1-gold-coverage-v1",
  "required_theme_ids": [
    "land_exchange",
    "water_wetlands",
    "migratory_birds",
    "cultural_tribal",
    "roadless",
    "forest_plan_consistency",
    "multi_forest_plan_trigger"
  ],
  "review_contracts": [
    {
      "eval_file": "v1_ecid_real_ea_eval.json",
      "package_authority": {
        "replay_context_path": "replay_contexts/v1-cg-ecid-compliance-review.json"
      },
      "review_id": "v1-cg-ecid-compliance-review"
    },
    {
      "eval_file": "v1_west_reservoir_real_ea_eval.json",
      "package_authority": {
        "replay_context_path": "replay_contexts/west-reservoir-67436.json"
      },
      "review_id": "west-reservoir-67436"
    },
    {
      "eval_file": "v1_south_plateau_real_ea_eval.json",
      "package_authority": {
        "intake_package_path": "../source_library/reviews/_intake/region1-expansion-south-plateau-landscape-treatment"
      },
      "review_id": "region1-expansion-south-plateau-landscape-treatment"
    }
  ],
  "schema_version": "gold-coverage-eval-v1",
  "version": "1.0.0"
}
