{
  "schema_version": "promotion-suite-v0",
  "id": "post-v1-region1-ea-promotion-suite",
  "label": "Post-V1 Region 1 EA promotion suite",
  "source_set_id": "source-set-ba8d0feae79501b8",
  "rule_pack_path": "config/compliance_rule_pack_nepa_ea_v0.json",
  "rule_pack_id": "nepa-ea-v0",
  "rule_pack_version": "0.4.0",
  "expected_rule_count": 44,
  "expected_baseline_source_record_count": 26,
  "review_cases": [
    {
      "id": "v1-cg-ecid",
      "label": "East Crazy Inspiration Divide V1 review",
      "review_id": "v1-cg-ecid-compliance-review",
      "package_label": "East Crazy Inspiration Divide Land Exchange",
      "required_for_current_promotion": true,
      "results": [
        {
          "id": "compliance_validation",
          "label": "Compliance validation",
          "path": "reviews/{review_id}/compliance_validation.json",
          "required_for_current_promotion": true,
          "failure_category": "stale_artifact",
          "checks": [
            {
              "name": "compliance_validation_passed",
              "json_path": "passed",
              "equals": true
            }
          ]
        },
        {
          "id": "compliance_review",
          "label": "Compliance review summary",
          "path": "reviews/{review_id}/compliance_review.json",
          "required_for_current_promotion": true,
          "failure_category": "unsupported_package_evidence",
          "checks": [
            {
              "name": "reviewer_ready",
              "json_path": "summary.reviewer_ready",
              "equals": true
            },
            {
              "name": "source_set_matches",
              "json_path": "summary.source_set_id",
              "equals": "source-set-ba8d0feae79501b8",
              "failure_category": "stale_artifact"
            },
            {
              "name": "generated_rule_pack_id_matches",
              "json_path": "summary.rule_pack_id",
              "equals": "generated-nepa-ea-v0-v1-cg-ecid-compliance-review",
              "failure_category": "stale_artifact"
            },
            {
              "name": "generated_rule_pack_version_matches",
              "json_path": "summary.rule_pack_version",
              "equals": "applicability-v0",
              "failure_category": "stale_artifact"
            },
            {
              "name": "rule_count",
              "json_path": "summary.rule_count",
              "equals": 33
            },
            {
              "name": "baseline_source_record_count",
              "json_path": "summary.baseline_source_record_count",
              "equals": 26,
              "failure_category": "missing_source"
            },
            {
              "name": "rule_claim_gaps",
              "json_path": "summary.rule_claim_gap_count",
              "equals": 0,
              "failure_category": "missing_source"
            }
          ]
        },
        {
          "id": "compliance_matrix",
          "label": "Compliance matrix JSON",
          "path": "reviews/{review_id}/compliance_matrix.json",
          "required_for_current_promotion": true,
          "failure_category": "stale_artifact",
          "checks": [
            {
              "name": "matrix_row_count",
              "json_path": "summary.row_count",
              "equals": 33
            },
            {
              "name": "matrix_reviewer_ready",
              "json_path": "summary.reviewer_ready",
              "equals": true
            }
          ]
        },
        {
          "id": "compliance_matrix_pdf",
          "label": "Compliance matrix PDF",
          "path": "reviews/{review_id}/compliance_matrix.pdf",
          "format": "binary",
          "required_for_current_promotion": true,
          "failure_category": "stale_artifact",
          "checks": [
            {
              "name": "matrix_pdf_header_valid",
              "starts_with": "%PDF-"
            }
          ]
        },
        {
          "id": "decision_support_report",
          "label": "EA consistency decision-support report",
          "path": "reviews/{review_id}/decision_support/ea_consistency_decision_support.json",
          "required_for_current_promotion": true,
          "failure_category": "stale_artifact",
          "checks": [
            {
              "name": "decision_support_schema",
              "json_path": "schema_version",
              "equals": "ea-consistency-decision-support-report-v1"
            },
            {
              "name": "decision_support_review_id",
              "json_path": "review_id",
              "equals": "v1-cg-ecid-compliance-review"
            },
            {
              "name": "decision_support_source_set",
              "json_path": "source_set_id",
              "equals": "source-set-ba8d0feae79501b8"
            },
            {
              "name": "decision_support_status",
              "json_path": "executive_determination.decision_support_status",
              "equals": "reviewer_ready"
            },
            {
              "name": "decision_support_validation_passed",
              "json_path": "validation_and_replay.passed",
              "equals": true
            },
            {
              "name": "decision_support_manifest_passed",
              "json_path": "manifest.validation_status",
              "equals": "passed"
            },
            {
              "name": "decision_support_applicable_authorities",
              "json_path": "applicable_authority_summary.applicable_authority_count",
              "equals": 33
            },
            {
              "name": "decision_support_non_applicable_authorities",
              "json_path": "non_applicable_authority_boundary.non_applicable_authority_count",
              "equals": 340
            },
            {
              "name": "decision_support_forest_plan_components",
              "json_path": "forest_plan_consistency.component_finding_count",
              "equals": 329
            },
            {
              "name": "decision_support_applicable_standards",
              "json_path": "forest_plan_consistency.applicable_standard_count",
              "equals": 12
            },
            {
              "name": "decision_support_legal_conclusion_boundary",
              "json_path": "executive_determination.legal_conclusion",
              "equals": false
            }
          ]
        },
        {
          "id": "decision_support_manifest",
          "label": "EA consistency decision-support manifest",
          "path": "reviews/{review_id}/decision_support/ea_consistency_decision_support_manifest.json",
          "required_for_current_promotion": true,
          "failure_category": "stale_artifact",
          "checks": [
            {
              "name": "decision_support_manifest_schema",
              "json_path": "schema_version",
              "equals": "ea-consistency-decision-support-manifest-v1"
            },
            {
              "name": "decision_support_manifest_review_id",
              "json_path": "review_id",
              "equals": "v1-cg-ecid-compliance-review"
            },
            {
              "name": "decision_support_manifest_source_set",
              "json_path": "source_set_id",
              "equals": "source-set-ba8d0feae79501b8"
            },
            {
              "name": "decision_support_manifest_validation_status",
              "json_path": "validation_status",
              "equals": "passed"
            }
          ]
        },
        {
          "id": "decision_support_pdf",
          "label": "EA consistency decision-support PDF",
          "path": "reviews/{review_id}/decision_support/ea_consistency_decision_support.pdf",
          "format": "binary",
          "required_for_current_promotion": true,
          "failure_category": "stale_artifact",
          "checks": [
            {
              "name": "decision_support_pdf_header_valid",
              "starts_with": "%PDF-"
            }
          ]
        },
        {
          "id": "authority_family_provenance",
          "label": "Authority-family provenance",
          "path": "reviews/{review_id}/authority_family_provenance.json",
          "required_for_current_promotion": true,
          "failure_category": "stale_artifact",
          "checks": [
            {
              "name": "authority_provenance_generated_mode",
              "json_path": "summary.generated_mode",
              "equals": true
            },
            {
              "name": "authority_provenance_finding_count",
              "json_path": "summary.finding_authority_provenance_count",
              "equals": 33
            },
            {
              "name": "authority_provenance_family_ids_present",
              "json_path": "summary.findings_missing_authority_family_ids",
              "equals": []
            },
            {
              "name": "authority_provenance_candidate_ids_present",
              "json_path": "summary.findings_missing_candidate_authority_ids",
              "equals": []
            }
          ]
        },
        {
          "id": "non_applicable_authority_appendix",
          "label": "Non-applicable authority appendix",
          "path": "reviews/{review_id}/non_applicable_authority_appendix.json",
          "required_for_current_promotion": true,
          "failure_category": "stale_artifact",
          "checks": [
            {
              "name": "non_applicable_authority_count",
              "json_path": "summary.non_applicable_authority_count",
              "min": 1
            },
            {
              "name": "non_applicable_authorities_have_coverage",
              "json_path": "summary.all_have_coverage_certificates",
              "equals": true
            },
            {
              "name": "non_applicable_authorities_have_rationale",
              "json_path": "summary.all_have_rationale",
              "equals": true
            }
          ]
        },
        {
          "id": "authority_reviewer_resolution_report",
          "label": "Authority reviewer-resolution report",
          "path": "reviews/{review_id}/authority_reviewer_resolution_report.json",
          "required_for_current_promotion": true,
          "failure_category": "adjudication_needed",
          "checks": [
            {
              "name": "authority_resolution_pending_count",
              "json_path": "summary.pending_resolution_count",
              "equals": 0
            },
            {
              "name": "authority_resolution_report_passed",
              "json_path": "summary.passed",
              "equals": true
            }
          ]
        },
        {
          "id": "litigation_risk_summary",
          "label": "Litigation-risk summary",
          "path": "reviews/{review_id}/litigation_risk_summary.json",
          "required_for_current_promotion": true,
          "failure_category": "unsupported_package_evidence",
          "checks": [
            {
              "name": "litigation_risk_flags_present",
              "json_path": "summary.risk_flag_count",
              "min": 1
            },
            {
              "name": "litigation_risk_no_legal_conclusions",
              "json_path": "summary.legal_conclusion_count",
              "equals": 0
            },
            {
              "name": "litigation_risk_deterministic_only",
              "json_path": "summary.deterministic_only",
              "equals": true
            }
          ]
        },
        {
          "id": "v1_ea_eval",
          "label": "V1 real EA eval",
          "path": "reviews/{review_id}/v1_ea_eval_results.json",
          "required_for_current_promotion": true,
          "failure_category": "unsupported_package_evidence",
          "checks": [
            {
              "name": "v1_eval_passed",
              "json_path": "summary.passed",
              "equals": true
            },
            {
              "name": "broader_ea_passed",
              "json_path": "summary.broader_ea_passed",
              "equals": true
            },
            {
              "name": "forest_plan_passed",
              "json_path": "summary.forest_plan_passed",
              "equals": true
            },
            {
              "name": "eval_source_set_matches",
              "json_path": "contract.source_set_id",
              "equals": "source-set-ba8d0feae79501b8",
              "failure_category": "stale_artifact"
            }
          ]
        }
      ]
    },
    {
      "id": "region1-expansion-ecid-preliminary-ea",
      "label": "ECID preliminary-EA expansion review",
      "review_id": "region1-expansion-ecid-preliminary-ea",
      "package_label": "East Crazy Inspiration Divide preliminary EA",
      "required_for_current_promotion": false,
      "results": [
        {
          "id": "applicability_validation",
          "label": "ECID applicability validation",
          "path": "reviews/{review_id}/applicability/applicability_validation.json",
          "required_for_current_promotion": false,
          "required_for_expansion": true,
          "failure_category": "adjudication_needed",
          "checks": [
            {
              "name": "applicability_validation_passed",
              "json_path": "summary.passed",
              "equals": true
            },
            {
              "name": "applicability_reviewer_ready",
              "json_path": "summary.reviewer_ready",
              "equals": true
            },
            {
              "name": "applicable_authority_count",
              "json_path": "summary.applicable_authority_count",
              "equals": 46
            },
            {
              "name": "non_applicable_authority_count",
              "json_path": "summary.non_applicable_authority_count",
              "equals": 346
            },
            {
              "name": "needs_adjudication_authority_count",
              "json_path": "summary.needs_adjudication_authority_count",
              "equals": 0
            }
          ]
        },
        {
          "id": "generated_rule_pack_validation",
          "label": "ECID generated rule-pack validation",
          "path": "reviews/{review_id}/applicability/generated_rule_pack_validation.json",
          "required_for_current_promotion": false,
          "required_for_expansion": true,
          "failure_category": "stale_artifact",
          "checks": [
            {
              "name": "generated_rule_pack_validation_passed",
              "json_path": "summary.passed",
              "equals": true
            },
            {
              "name": "generated_rule_pack_ready",
              "json_path": "summary.generated_rule_pack_ready",
              "equals": true
            },
            {
              "name": "generated_rule_count",
              "json_path": "summary.generated_rule_count",
              "equals": 46
            },
            {
              "name": "applicable_authority_count",
              "json_path": "summary.applicable_authority_count",
              "equals": 46
            },
            {
              "name": "source_set_matches",
              "json_path": "summary.source_set_id",
              "equals": "source-set-ba8d0feae79501b8",
              "failure_category": "stale_artifact"
            }
          ]
        },
        {
          "id": "compliance_validation",
          "label": "ECID compliance validation",
          "path": "reviews/{review_id}/compliance_validation.json",
          "required_for_current_promotion": false,
          "required_for_expansion": true,
          "failure_category": "forest_plan_reviewer_not_ready",
          "checks": [
            {
              "name": "compliance_validation_passed",
              "json_path": "passed",
              "equals": true
            }
          ]
        },
        {
          "id": "compliance_review",
          "label": "ECID compliance review summary",
          "path": "reviews/{review_id}/compliance_review.json",
          "required_for_current_promotion": false,
          "required_for_expansion": true,
          "failure_category": "forest_plan_reviewer_not_ready",
          "checks": [
            {
              "name": "reviewer_ready",
              "json_path": "summary.reviewer_ready",
              "equals": true
            },
            {
              "name": "source_set_matches",
              "json_path": "summary.source_set_id",
              "equals": "source-set-ba8d0feae79501b8",
              "failure_category": "stale_artifact"
            },
            {
              "name": "generated_rule_pack_id_matches",
              "json_path": "summary.rule_pack_id",
              "equals": "generated-nepa-ea-v0-region1-expansion-ecid-preliminary-ea",
              "failure_category": "stale_artifact"
            },
            {
              "name": "generated_rule_pack_version_matches",
              "json_path": "summary.rule_pack_version",
              "equals": "applicability-v0",
              "failure_category": "stale_artifact"
            },
            {
              "name": "rule_count",
              "json_path": "summary.rule_count",
              "equals": 46
            },
            {
              "name": "baseline_source_record_count",
              "json_path": "summary.baseline_source_record_count",
              "equals": 26,
              "failure_category": "missing_source"
            },
            {
              "name": "rule_claim_gap_count",
              "json_path": "summary.rule_claim_gap_count",
              "equals": 0,
              "failure_category": "missing_source"
            },
            {
              "name": "forest_plan_applicable_standard_count",
              "json_path": "summary.forest_plan_review.component_evaluation.applicable_standard_count",
              "equals": 29,
              "failure_category": "forest_plan_reviewer_not_ready"
            },
            {
              "name": "forest_plan_applied_standard_count",
              "json_path": "summary.forest_plan_review.component_evaluation.applied_standard_count",
              "equals": 7,
              "failure_category": "forest_plan_reviewer_not_ready"
            }
          ]
        },
        {
          "id": "compliance_matrix",
          "label": "ECID compliance matrix JSON",
          "path": "reviews/{review_id}/compliance_matrix.json",
          "required_for_current_promotion": false,
          "required_for_expansion": true,
          "failure_category": "forest_plan_reviewer_not_ready",
          "checks": [
            {
              "name": "matrix_row_count",
              "json_path": "summary.row_count",
              "equals": 46
            },
            {
              "name": "matrix_forest_plan_row_count",
              "json_path": "summary.forest_plan_compliance_row_count",
              "equals": 178
            },
            {
              "name": "matrix_reviewer_ready",
              "json_path": "summary.reviewer_ready",
              "equals": true
            }
          ]
        },
        {
          "id": "compliance_matrix_pdf",
          "label": "ECID compliance matrix PDF",
          "path": "reviews/{review_id}/compliance_matrix.pdf",
          "format": "binary",
          "required_for_current_promotion": false,
          "required_for_expansion": true,
          "failure_category": "stale_artifact",
          "checks": [
            {
              "name": "matrix_pdf_header_valid",
              "starts_with": "%PDF-"
            }
          ]
        },
        {
          "id": "authority_family_provenance",
          "label": "ECID authority-family provenance",
          "path": "reviews/{review_id}/authority_family_provenance.json",
          "required_for_current_promotion": false,
          "required_for_expansion": true,
          "failure_category": "stale_artifact",
          "checks": [
            {
              "name": "authority_provenance_generated_mode",
              "json_path": "summary.generated_mode",
              "equals": true
            },
            {
              "name": "authority_provenance_finding_count",
              "json_path": "summary.finding_authority_provenance_count",
              "equals": 46
            },
            {
              "name": "authority_resolution_pending_count",
              "json_path": "summary.pending_resolution_count",
              "equals": 0
            }
          ]
        },
        {
          "id": "non_applicable_authority_appendix",
          "label": "ECID non-applicable authority appendix",
          "path": "reviews/{review_id}/non_applicable_authority_appendix.json",
          "required_for_current_promotion": false,
          "required_for_expansion": true,
          "failure_category": "stale_artifact",
          "checks": [
            {
              "name": "non_applicable_authority_count",
              "json_path": "summary.non_applicable_authority_count",
              "equals": 346
            },
            {
              "name": "non_applicable_authorities_have_coverage",
              "json_path": "summary.all_have_coverage_certificates",
              "equals": true
            },
            {
              "name": "non_applicable_authorities_have_rationale",
              "json_path": "summary.all_have_rationale",
              "equals": true
            }
          ]
        },
        {
          "id": "forest_plan_component_adjudication_template",
          "label": "ECID forest-plan component adjudication worklist",
          "path": "reviews/{review_id}/forest_plan_component_adjudication_template.json",
          "required_for_current_promotion": false,
          "required_for_expansion": true,
          "failure_category": "forest_plan_reviewer_not_ready",
          "checks": [
            {
              "name": "component_adjudication_template_pending_items",
              "json_path": "summary.pending_item_count",
              "equals": 158
            },
            {
              "name": "component_adjudication_template_queue_items",
              "json_path": "summary.queue_item_count",
              "equals": 158
            }
          ]
        },
        {
          "id": "phase_eval",
          "label": "ECID review-scoped phase eval",
          "path": "reviews/{review_id}/phase_eval_results.json",
          "required_for_current_promotion": false,
          "required_for_expansion": true,
          "failure_category": "forest_plan_reviewer_not_ready",
          "checks": [
            {
              "name": "phase_eval_review_id_matches",
              "json_path": "review_id",
              "equals": "region1-expansion-ecid-preliminary-ea",
              "failure_category": "stale_artifact"
            },
            {
              "name": "phase_eval_source_set_matches",
              "json_path": "source_set_id",
              "equals": "source-set-ba8d0feae79501b8",
              "failure_category": "stale_artifact"
            },
            {
              "name": "phase_eval_passed",
              "json_path": "passed",
              "equals": true
            },
            {
              "name": "phase_eval_reviewer_ready",
              "json_path": "reviewer_ready",
              "equals": true
            }
          ]
        }
      ]
    }
  ],
  "suite_results": [
    {
      "id": "phase_eval_core",
      "label": "Core phase eval readiness",
      "path": "derived/{source_set_id}/evidence_graph/phase_eval_results.json",
      "required_for_current_promotion": true,
      "failure_category": "stale_artifact",
      "checks": [
        {
          "name": "phase_source_set_matches",
          "json_path": "source_set_id",
          "equals": "source-set-ba8d0feae79501b8"
        },
        {
          "name": "core_passed_phase_count",
          "json_path": "passed_phase_count",
          "min": 17
        },
        {
          "name": "core_reviewer_ready_phase_count",
          "json_path": "reviewer_ready_phase_count",
          "min": 17
        },
        {
          "name": "phase_eval_arbitration_summary_schema",
          "json_path": "applicability_arbitration_summary.schema_version",
          "equals": "applicability-arbitration-summary-v0",
          "failure_category": "applicability_miss"
        },
        {
          "name": "phase_eval_arbitration_decision_count",
          "json_path": "applicability_arbitration_summary.decision_count",
          "min": 1,
          "failure_category": "applicability_miss"
        }
      ]
    },
    {
      "id": "post_v1_applicability_phase",
      "label": "Post-V1 applicability phase readiness",
      "path": "derived/{source_set_id}/evidence_graph/phase_eval_results.json",
      "required_for_current_promotion": false,
      "required_for_expansion": true,
      "failure_category": "applicability_miss",
      "checks": [
        {
          "name": "phase_eval_reviewer_ready_with_applicability",
          "json_path": "reviewer_ready",
          "equals": true,
          "failure_category": "applicability_miss"
        }
      ]
    },
    {
      "id": "compliance_review_eval",
      "label": "Compliance review eval",
      "path": "reviews/compliance_review_eval/compliance_review_eval_results.json",
      "required_for_current_promotion": true,
      "failure_category": "unsupported_package_evidence",
      "checks": [
        {
          "name": "compliance_review_eval_passed",
          "json_path": "passed",
          "equals": true
        },
        {
          "name": "compliance_review_eval_cases",
          "json_path": "passed_count",
          "min": 3
        },
        {
          "name": "compliance_review_eval_source_set",
          "json_path": "source_set_id",
          "equals": "source-set-ba8d0feae79501b8",
          "failure_category": "stale_artifact"
        }
      ]
    },
    {
      "id": "compliance_gold_eval",
      "label": "Compliance gold eval",
      "path": "reviews/compliance_gold_eval/compliance_gold_eval_results.json",
      "required_for_current_promotion": true,
      "failure_category": "adjudication_needed",
      "checks": [
        {
          "name": "compliance_gold_eval_passed",
          "json_path": "passed",
          "equals": true
        },
        {
          "name": "compliance_gold_eval_cases",
          "json_path": "passed_case_count",
          "min": 10
        },
        {
          "name": "compliance_gold_rule_pack_version",
          "json_path": "rule_pack_version",
          "equals": "0.4.0",
          "failure_category": "stale_artifact"
        }
      ]
    },
    {
      "id": "applicability_eval_authority_family_coverage",
      "label": "Applicability eval authority-family coverage",
      "path": "reviews/applicability_eval/applicability_eval_results.json",
      "required_for_current_promotion": true,
      "failure_category": "applicability_miss",
      "checks": [
        {
          "name": "applicability_eval_passed",
          "json_path": "passed",
          "equals": true
        },
        {
          "name": "applicability_eval_case_count",
          "json_path": "case_count",
          "min": 9
        },
        {
          "name": "authority_family_high_priority_count",
          "json_path": "authority_family_template_coverage.high_priority_family_count",
          "equals": 19
        },
        {
          "name": "authority_family_positive_coverage",
          "json_path": "authority_family_template_coverage.positive_covered_family_count",
          "equals": 19
        },
        {
          "name": "authority_family_negative_coverage",
          "json_path": "authority_family_template_coverage.negative_covered_family_count",
          "equals": 19
        },
        {
          "name": "authority_family_unresolved_coverage",
          "json_path": "authority_family_template_coverage.unresolved_covered_family_count",
          "min": 1
        },
        {
          "name": "authority_family_real_package_tags",
          "json_path": "authority_family_template_coverage.real_package_coverage_passed",
          "equals": true
        },
        {
          "name": "applicability_eval_weak_auxiliary_arbitration",
          "json_path": "arbitration_summary.applicable_with_weak_auxiliary_count",
          "min": 1
        },
        {
          "name": "applicability_eval_weak_only_arbitration",
          "json_path": "arbitration_summary.weak_positive_only_needs_adjudication_count",
          "min": 1
        },
        {
          "name": "applicability_eval_positive_negative_arbitration",
          "json_path": "arbitration_summary.positive_negative_conflict_needs_adjudication_count",
          "min": 1
        }
      ]
    },
    {
      "id": "applicability_gold_eval_authority_family_adjudication",
      "label": "Applicability gold eval authority-family adjudication coverage",
      "path": "reviews/applicability_gold_eval/applicability_gold_eval_results.json",
      "required_for_current_promotion": true,
      "failure_category": "adjudication_needed",
      "checks": [
        {
          "name": "applicability_gold_eval_passed",
          "json_path": "passed",
          "equals": true
        },
        {
          "name": "applicability_gold_eval_promotion_ready",
          "json_path": "promotion_ready",
          "equals": true
        },
        {
          "name": "applicability_gold_eval_case_count",
          "json_path": "case_count",
          "min": 5
        },
        {
          "name": "applicability_gold_eval_weak_only_arbitration",
          "json_path": "arbitration_summary.weak_positive_only_needs_adjudication_count",
          "min": 1
        },
        {
          "name": "applicability_gold_eval_unresolved_profile",
          "json_path": "profile_counts.unresolved",
          "min": 1
        },
        {
          "name": "applicability_gold_eval_adjudicated_profile",
          "json_path": "profile_counts.adjudicated",
          "min": 1
        },
        {
          "name": "authority_family_adjudicated_coverage",
          "json_path": "authority_family_template_coverage.adjudicated_covered_family_count",
          "min": 1
        }
      ]
    }
  ],
  "expansion_slots": [
    {
      "id": "region1-real-ea-slot-1",
      "label": "Second real Region 1 EA package: ECID preliminary EA",
      "status": "blocked_source_claim_and_forest_plan_component_adjudication",
      "ready": false,
      "required_for_current_promotion": false,
      "failure_category": "forest_plan_reviewer_not_ready",
      "review_id": "region1-expansion-ecid-preliminary-ea",
      "package_path": "source_library/reviews/_intake/demo-ea-2026-04-30/East Crazy Inspiration Divide Land Exchange (63115)/Preliminary Environmental Assessment",
      "last_local_signal": {
        "package_file_count": 7,
        "package_chunk_count": 160,
        "candidate_authority_count": 392,
        "applicable_authority_count": 46,
        "non_applicable_authority_count": 346,
        "needs_adjudication_authority_count": 0,
        "unresolved_authority_count": 0,
        "remaining_adjudication_authority_family_ids": [],
        "applicability_validation_passed": true,
        "generated_rule_pack_ready": true,
        "generated_rule_count": 46,
        "compliance_validation_passed": false,
        "compliance_review_reviewer_ready": false,
        "rule_claim_link_count": 127,
        "rule_claim_gap_count": 17,
        "forest_plan_applicable_standard_count": 29,
        "forest_plan_applied_standard_count": 7,
        "forest_plan_component_reviewer_resolution_count": 158,
        "forest_plan_component_adjudication_template_pending_count": 158,
        "adjudication_template_path": "source_library/reviews/region1-expansion-ecid-preliminary-ea/applicability/applicability_adjudication_template.json",
        "forest_plan_component_adjudication_template_path": "source_library/reviews/region1-expansion-ecid-preliminary-ea/forest_plan_component_adjudication_template.json",
        "phase_eval_passed": false,
        "phase_eval_reviewer_ready": false
      },
      "next_action": "Close the 17 ECID rule-claim gaps first, then complete the 158-item forest-plan component adjudication worklist, run forest-plan-component-adjudication-eval, and rerun ECID compliance review and review-scoped phase eval before marking this slot ready.",
      "acceptance_signal": "The preliminary-EA review passes applicability validation and phase-eval without weakening source-record, document-role, citation, section, forest-plan, or validation gates."
    },
    {
      "id": "region1-real-ea-slot-2",
      "label": "Third real Region 1 EA package",
      "status": "open",
      "ready": false,
      "required_for_current_promotion": false,
      "failure_category": "package_fixture_missing",
      "next_action": "Add a package from a different forest/profile or document shape to expose extraction, retrieval, applicability, and adjudication gaps.",
      "acceptance_signal": "Typed failures are either closed through general retrieval/eval improvements or retained as explicit reviewer work."
    }
  ]
}
